{
  "meta": {
    "code": "603938",
    "name": "三孚股份",
    "exchange": "SH",
    "shenwan_industry": "基础化工/化学原料",
    "concept_tags": ["三氯氢硅", "高纯四氯化硅", "电子级特气", "光纤预制棒", "硅烷偶联剂", "台积电供应商", "存储芯片", "循环经济", "有机硅"],
    "analysis_date": "2026-07-10",
    "fiscal_period": "2026Q1",
    "confidence": 3,
    "status": "active",
    "last_updated": "2026-07-10T04:44:00"
  },
  "overview": {
    "full_name": "唐山三孚硅业股份有限公司",
    "market": "上交所主板",
    "listed_since": "2017-06-28",
    "total_market_cap_yi": 204,
    "float_market_cap_yi": 204,
    "pe_ttm": 131.6,
    "pb": 8.1,
    "controller": "孙任靖(40.16%)+唐山元亨科技(26.39%)为一致行动人，合计持股66.55%。民营企业，实际控制人孙任靖",
    "employees": 1054,
    "one_liner": "国内三氯氢硅/高纯四氯化硅龙头，电子级二氯二氢硅已打入台积电供应链，从基础化工向半导体电子特气升级的「循环经济」特色化工企业",
    "revenue_segments": [
      {"segment": "硅系列产品(三氯氢硅/四氯化硅/硅烷偶联剂)", "revenue_pct": 45.0, "gross_margin_pct": 12.0, "yoy_growth_pct": -5.0},
      {"segment": "钾系列产品(氢氧化钾/硫酸钾)", "revenue_pct": 30.0, "gross_margin_pct": 18.0, "yoy_growth_pct": 30.0},
      {"segment": "高纯四氯化硅(光纤级)", "revenue_pct": 15.0, "gross_margin_pct": 25.0, "yoy_growth_pct": 20.0},
      {"segment": "电子级特气(二氯二氢硅/三氯氢硅)", "revenue_pct": 2.0, "gross_margin_pct": 40.0, "yoy_growth_pct": 50.0}
    ]
  },
  "supply_chain": {
    "position": "精细化工制造，处于化工产业链中游。以三氯氢硅为核心，构建「四硅-两气-两钾」循环经济产业链。上游为硅粉/氯化氢/焦炭等基础原料，下游覆盖光伏(多晶硅)、光纤(预制棒)、半导体(电子特气)、钾肥等行业",
    "upstream": "硅粉(工业硅供应商，如合盛硅业/新安股份)、氯化氢(自产+外购)、焦炭(还原剂，来自焦化企业)、电力(自备电厂+外购，唐山能源成本较低)",
    "downstream": "多晶硅企业(光伏级三氯氢硅，如大全能源/通威股份)、光纤预制棒企业(高纯四氯化硅，如长飞光纤/亨通光电)、半导体晶圆厂(电子级特气，台积电/中芯国际)、钾肥/化工下游",
    "upstream_bargaining": {"level": "中", "reason": "工业硅产能过剩价格低迷有利采购，但硅粉/氯化氢等基础原料市场化程度高，价格随行就市。自备电厂+唐山低能源成本提供一定议价优势"},
    "downstream_bargaining": {"level": "弱", "reason": "光伏级三氯氢硅竞争激烈(新安/宏柏/合盛等多家供应)，议价能力弱。但高纯四氯化硅(光纤级)国内市占率较高，有一定议价权；电子级特气(台积电)认证壁垒高、供应稀缺、议价能力较强"},
    "substitution_risk": {"level": "中", "by_whom": "光伏级三氯氢硅可被新安股份/宏柏新材/江瀚新材等替代，产品同质化程度高。高纯四氯化硅和电子级特气因认证壁垒替代风险较低", "cycle_years": 3},
    "supply_constraints": {
      "capacity_bottleneck": "电子级特气产能较小(二氯二氢硅500吨/三氯氢硅1000吨/四氯化硅500吨)，2025年产能利用率较低(电子特气收入占比仅1-2%)；高纯四氯化硅3万吨产能目前基本满负荷",
      "license_barrier": "电子级二氯二氢硅已通过台积电多次质量验证并实现首批供货(约40万元)，认证壁垒高但产能和放量仍需时间。电子级三氯氢硅面向12寸大硅片/碳化硅外延，验证周期1-2年",
      "key_material_dependency": "电子级产品对纯度要求极高(6N-9N级)，精馏技术和设备依赖进口；高纯四氯化硅原材料为自产四氯化硅(三氯氢硅联产物)，原料自给有成本优势",
      "has_hard_constraint": false
    }
  },
  "moat": {
    "scores": {
      "tech_barrier": {"score": 3, "detail": "电子级二氯二氢硅通过台积电认证是国内少数，但产能仅500吨/年体量很小。高纯四氯化硅9N级技术有一定壁垒，国内光纤预制棒用高纯四氯化硅主要供应商之一。整体技术壁垒在基础化工中偏高、在半导体材料中偏低"},
      "scale_effect": {"score": 3, "detail": "三氯氢硅产能~6.5万吨/年国内前列，高纯四氯化硅3万吨/年国内领先，氢氧化钾8万吨/年有一定规模。2025年营收20.97亿在化工行业中属于中型企业，规模效应有限"},
      "customer_stickiness": {"score": 2, "detail": "光伏级三氯氢硅产品同质化高、客户切换成本低；高纯四氯化硅以长协为主、有一定粘性；电子级特气认证后粘性强但占比极低(收入占比1-2%)。整体客户粘性偏弱"},
      "brand_patent_license": {"score": 3, "detail": "参与修定工业三氯氢硅国家标准(GB/T28654-2018)，子公司参与制定电子工业用二氯硅烷/四氯化硅国家标准。CNAS实验室+河北省A级研发机构。但专利和品牌在半导体材料领域不及专业特气公司"},
      "cost_advantage": {"score": 4, "detail": "「四硅-两气-两钾」循环经济模式使物料和能源在企业内部高效利用，原材料耗用减量化、能源消耗最低化、污染物排放最小化。唐山地区能源成本较低(自备电厂+煤炭资源丰富)，综合成本较同行低15%。2026Q1毛利率16.30%为化工行业中偏上水平"}
    },
    "trend_3_5yr": "维持",
    "core_risk": "光伏级三氯氢硅受多晶硅产能过剩拖累需求和价格；电子级特气产能小、放量慢，短期难以对业绩形成实质性贡献；主营产品同质化程度高导致毛利率持续承压(从2022年~30%降至2025年13.33%)"
  },
  "financials": {
    "periods": ["2023", "2024", "2025", "2026Q1"],
    "metrics": {
      "revenue_yi": [21.29, 17.70, 20.97, 6.47],
      "net_profit_yi": [1.78, 0.64, 0.80, 0.39],
      "gross_margin_pct": [23.0, 14.11, 13.33, 16.30],
      "net_margin_pct": [8.4, 3.45, 3.81, 6.0],
      "roe_pct": [10.0, 2.65, 3.26, 1.54],
      "debt_ratio_pct": [25.0, 21.79, 23.0, 27.13],
      "ocf_to_profit": [1.5, 2.5, 0.95, 0.19],
      "rd_ratio_pct": [5.0, 6.0, 7.0, null],
      "ar_turnover_days": [35, 45, 72, null],
      "inventory_turnover_days": [50, 70, 82, null]
    },
    "highlights": [
      "2026Q1营收6.47亿(+30.91%)和净利0.39亿(+43.88%)双双高增，钾系列和硅烷偶联剂产品量价齐升是主因，盈利能力触底回升迹象明显",
      "资产负债率仅27.13%，现金资产充裕、财务结构健康。上市以来持续分红(2025年10派0.22元)，经营风格稳健",
      "高纯四氯化硅自2025Q4产能利用率提升至基本满负荷，光纤预制棒市场需求回暖带动产品景气度回升"
    ],
    "risk_points": [
      "毛利率持续下滑：从2023年约23%降至2025年13.33%，光伏级三氯氢硅价格低迷+竞争加剧是核心原因，盈利能力尚未见底",
      "电子特气业务体量极小：2025年电子特气收入占总收入仅1-2%，虽已打入台积电供应链但放量仍需时日(首批订单仅40万元)，短期无法对冲传统业务下行",
      "应收账款体量较大：应收账款/利润达173%(2025年报)，营收增长伴随应收同步攀升(Q1 2026应收同比+32%)，需警惕坏账风险",
      "净利绝对值极低：2025全年净利仅0.80亿，对应200亿+市值PE高达254倍(静态)，估值严重脱离基本面"
    ]
  },
  "growth": {
    "short_term_6m": [
      "2026Q2业绩有望延续Q1高增态势：硅烷偶联剂销量Q1同比+60%，新产能(14,000吨技改扩建)持续推进，下半年贡献增量",
      "高纯四氯化硅目前满负荷运行(3万吨/年)，光纤预制棒需求回暖带动产品价格企稳回升",
      "钾系列产品(氢氧化钾/硫酸钾)受益钾肥景气回升，Q1贡献主要收入增量"
    ],
    "mid_term_18m": [
      "电子级二氯二氢硅/三氯氢硅/四氯化硅合计产能2000吨/年，目前产能利用率低，若下游认证突破和放量将大幅提升电子特气收入占比",
      "硅烷偶联剂二期73,000吨规划产能持续推进，一期15,000吨中间体+技改扩建14,000吨逐步释放，打开有机硅增长空间",
      "TEOS(高纯正硅酸乙酯)8000吨/年产能处于市场认证阶段，面向电子级/CMP/碳化硅/合成石英等高端领域",
      "SOD(旋涂介电材料)项目一期40吨/年预计2027Q1试生产，面向先进封装/半导体前道工艺，是向半导体材料深化的关键布局"
    ],
    "long_term_5y": [
      "电子级特气国产替代大逻辑：随国内晶圆厂扩产(中芯国际/长江存储/长鑫存储)，电子级氯硅烷类特气需求持续增长，三孚作为台积电认证供应商有望逐步放量",
      "从基础化工向半导体材料转型：「三氯氢硅→高纯四氯化硅→电子级特气→SOD/TEOS」产品线不断向高附加值延伸，长期有望提升整体毛利率和估值中枢",
      "全球光纤到户+5G/6G建设驱动高纯四氯化硅长期需求，公司作为国内主要供应商将持续受益"
    ],
    "tam_yi": 300,
    "penetration_pct": 7.0,
    "ceiling": "国内三氯氢硅市场约46万吨/年(2025年)，公司产能6.5万吨/年份额约14%；高纯四氯化硅(光纤级)市场空间约20-30亿/年，公司份额较高。电子级特气国内市场规模约280亿，公司当前占比极低，成长空间大但追赶难度也大"
  },
  "competition": {
    "rivals": [
      {"name": "新安股份", "code": "600596", "market_cap": "~350亿", "tech_gap": "从上游硅矿到下游有机硅全产业链布局，三氯氢硅产能8万吨/年(略高于三孚6.5万吨)。硅基材料基础产品收入26.86亿(2024年)，规模显著大于三孚", "share_comparison": "三氯氢硅产能接近、但新安全产业链一体化程度更深、营收规模更大", "differentiation": "作物保护+硅基新材料双主业，产业链更长；三孚专注氯硅烷细分+向电子级升级"},
      {"name": "宏柏新材", "code": "605366", "market_cap": "~60亿", "tech_gap": "三氯氢硅+硅烷偶联剂为主要产品，产能规模与三孚相近。但在高纯四氯化硅和电子级特气领域布局较少", "share_comparison": "三氯氢硅产能相当，但三孚在高纯四氯化硅和电子级有差异化优势", "differentiation": "侧重硅烷偶联剂下游应用；三孚在光纤级四氯化硅+电子特气领域领先"},
      {"name": "合盛硅业", "code": "603260", "market_cap": "~800亿", "tech_gap": "国内最大工业硅+有机硅一体化企业，工业硅产能全国第一。三氯氢硅为配套产品，规模较大但非核心业务", "share_comparison": "体量和综合实力远超三孚，但高纯四氯化硅和电子级特气并非合盛重点方向", "differentiation": "工业硅-有机硅全产业链巨头；三孚深耕氯硅烷精细化加工，走差异化路线"},
      {"name": "江瀚新材", "code": "603281", "market_cap": "~80亿", "tech_gap": "功能性硅烷(硅烷偶联剂)为主要产品，三氯氢硅自用为主。在硅烷偶联剂品类丰富度上领先三孚", "share_comparison": "硅烷偶联剂品种更多，但三孚的基础化工+电子级产品线更宽", "differentiation": "硅烷偶联剂专精；三孚向上游原料(三氯氢硅)+光纤/电子级延伸"}
    ],
    "porter_five": {"new_entrants": "中", "supplier_power": "中", "buyer_power": "高", "substitutes": "中", "rivalry": "高"}
  },
  "governance": {
    "core_team": "董事长/实控人孙任靖(持股40.16%)，总经理董立强。管理层以化工行业经验为主，近年逐步引入半导体材料领域人才(参与台积电认证)。核心团队稳定",
    "incentive_alignment": "孙任靖+元亨科技合计持股66.55%，实控人利益高度绑定。2026年推出员工持股计划，激励覆盖面扩大。但2026年2月高管董立强/张宪民小幅减持(合计2.79万股)，虽体量不大但信号偏负面",
    "board_structure": "民营企业，孙任靖控股。董事会设有独立董事(石瑛/宋晓阳/闫丙旗)，治理结构规范但决策权高度集中",
    "integrity_record": "无财务造假/违规重大前科。高管减持体量小(合计2.79万股约80万元)，不构成重大治理风险。经营风格稳健、上市以来持续分红",
    "shareholder_structure": {"institutional_pct": 27.22, "retail_pct": 33.22, "shareholder_count_trend": "股东户数36182(Q1 2026)，较2025年底34925增加3.6%，筹码小幅分散。仅1只基金持仓(广发创新升级灵活配置60万股)，机构关注度极低"}
  },
  "fund_attention": {
    "holding_funds_count": 1,
    "total_holding_shares_wan": 60.0,
    "holding_pct_of_float": 0.16,
    "qoq_change": "较2025Q4(基金20家/持股138.44万股)大幅减少，仅剩广发创新升级灵活配置1只基金(60万股，新进)。基金关注度极低",
    "new_entries": 1,
    "exits": 20,
    "heavy_position_rank": null,
    "star_manager_holdings": ["广发创新升级灵活配置混合(60万股，新进，占流通股0.16%)"],
    "recent_research_visits": 5,
    "trend": "下降",
    "score": 2,
    "comment": "基金持仓从2025Q4的20家骤降至仅1家，机构关注度极低。2026年5月18日有一次集中调研(国信/华泰/华夏/兴证全球4家机构参与)，但尚未转化为实际持仓。电子特气概念虽好但短期业绩贡献极低，机构仍在观望。"
  },
  "valuation": {
    "current": {"pe_ttm": 131.6, "pe_percentile": 95, "pe_industry_median": 30.0, "pb": 8.1, "pb_percentile": 92, "pb_industry_median": 2.5, "ps_ttm": 9.7, "ps_industry_median": 2.0, "ev_ebitda": 80.0, "ev_ebitda_industry_median": 18.0},
    "scenarios": {
      "bull": {"assumptions": "2026E净利1.2亿(+50%)，硅烷偶联剂放量+高纯四氯化硅满产+电子级特气小批量贡献，市场给予电子特气估值溢价70x PE", "target_market_cap_yi": 84, "target_price": 21.9, "upside_pct": 64.7},
      "base": {"assumptions": "2026E净利0.95亿(+19%)，传统业务温和增长+电子特气微利。给予45x PE(化工向电子材料转型的估值中枢)", "target_market_cap_yi": 43, "target_price": 11.2, "downside_pct": 15.7},
      "bear": {"assumptions": "2026E净利0.65亿(-19%)，光伏级三氯氢硅持续低迷+电子特气放量不及预期。给予30x PE(回归基础化工估值)", "target_market_cap_yi": 19.5, "target_price": 5.1, "downside_pct": 61.6}
    }
  },
  "risks": [
    {"risk": "光伏级三氯氢硅持续低迷：多晶硅产能过剩(2025年产量同比-28.4%)导致三氯氢硅需求承压，价格和毛利率持续下行", "probability": "高", "impact": "高", "mitigation": "跟踪多晶硅开工率和三氯氢硅价格走势；公司正在降低光伏级占比、提升电子级和光纤级高附加值产品比重"},
    {"risk": "电子特气放量远低于预期：电子级产品2025年收入占总收入仅1-2%，台积电首批订单仅40万元，从「认证通过」到「批量供货」的鸿沟巨大", "probability": "中", "impact": "高", "mitigation": "跟踪每季电子特气收入占比变化和客户拓展数量；SOD/TEOS项目进度是关键验证节点"},
    {"risk": "产品同质化竞争加剧：三氯氢硅和氢氧化钾等传统产品门槛低，新安/宏柏/合盛等竞争对手规模更大、成本更低，利润空间被持续压缩", "probability": "高", "impact": "中", "mitigation": "关注公司产品结构升级速度(高纯四氯化硅/硅烷偶联剂/电子级占比提升)"},
    {"risk": "高估值泡沫风险：PE(TTM)131倍完全脱离基本面，市值204亿对应年净利仅0.80亿，主要靠「电子特气+台积电」概念支撑。若概念退潮估值将剧烈回归", "probability": "高", "impact": "高", "mitigation": "不建议在高位追入；关注净利能否在2-3年内增长至2亿+以消化当前估值"}
  ],
  "catalysts": [
    {"time_window": "2026年7-8月", "event": "2026半年报披露", "expected_impact": "若Q2延续Q1高增(+30%以上营收增速)，验证钾系列和硅烷偶联剂景气回升，可能催化估值修复", "certainty": "高"},
    {"time_window": "2026年下半年", "event": "电子级二氯二氢硅对台积电批量供货放量", "expected_impact": "从首批40万→月供百万级别需验证，若能实现将催化电子特气估值重估", "certainty": "中"},
    {"time_window": "2027年Q1", "event": "SOD(旋涂介电材料)项目一期40吨/年试生产", "expected_impact": "面向先进封装/半导体前道工艺，若试产成功将标志公司真正进入半导体核心材料领域", "certainty": "低"},
    {"time_window": "2026-2027年", "event": "TEOS(高纯正硅酸乙酯)8000吨/年获得市场认证", "expected_impact": "应用于电子级/CMP/碳化硅/合成石英，市场空间大，认证周期6-12个月", "certainty": "中"},
    {"time_window": "2026年下半年", "event": "硅烷偶联剂技改扩建14,000吨产能释放", "expected_impact": "Q1偶联剂销量已同比+60%，新产能释放将进一步增厚收入", "certainty": "高"}
  ],
  "verdict": {
    "core_thesis": "三孚股份处于从传统基础化工向半导体电子特气转型的关键期。传统业务(三氯氢硅/氢氧化钾)提供营收底盘但毛利率持续下滑，电子级特气(台积电认证)是估值想象空间的核心但短期贡献极低(收入占比1-2%)。当前PE 131倍严重脱离基本面(年净利仅0.80亿)，估值由「电子特气+台积电」概念支撑，存在较大泡沫风险。建议等待电子特气放量证据明确后再评估。",
    "long_reasons": [
      "电子级二氯二氢硅已通过台积电认证，是国内稀缺的台积电电子特气供应商，认证壁垒高，长期国产替代空间大(国内电子特气自给率仅~20%)",
      "「循环经济」模式构筑成本护城河：四硅-两气-两钾产业链物料和能源高效利用，成本低于同行~15%，在传统业务下行周期中保持了一定抗压能力",
      "产品线持续向高附加值延伸：三氯氢硅→高纯四氯化硅(光纤级)→电子级特气→SOD/TEOS(半导体前道)，技术升级路径清晰，若SOD 2027年试产成功将是重大飞跃"
    ],
    "short_reasons": [
      "PE 131倍完全脱离基本面：2025年净利仅0.80亿对应204亿市值，传统化工同行PE仅15-25倍。电子特气收入占比1-2%、2025年产能利用率低，概念远大于实质",
      "毛利率从2023年~23%降至2025年13.33%，光伏级三氯氢硅受多晶硅产能过剩严重拖累，传统业务仍未见底。钾系列Q1景气回升能否持续存疑",
      "电子特气放量路径漫长且不确定：台积电认证后首批订单仅40万元，「认证」到「批量」可能需要2-3年。SOD/TEOS仍处于建设/认证阶段，量产时间表反复延迟"
    ],
    "rating": "回避",
    "suggested_position_pct": 0.0,
    "holding_period": "短线",
    "entry_strategy": "不建议当前价位参与。若电子特气季度收入占比突破5%+连续2季营收增速>20%+毛利率回升至18%以上，可重新评估。合理建仓价位建议等待回落至10元以下(对应2026E PE ~40x)",
    "stop_loss_conditions": "目前不入，若已持有建议反弹减仓。跌破5.5元(对应PB ~2x)止损",
    "key_tracking_metrics": ["电子特气季度收入占比(当前1-2%，关键阈值5%)", "季度毛利率趋势(当前16.30%，需回升至18%+验证产品结构升级)", "台积电/中芯国际电子级产品采购量(验证从认证到放量的关键信号)", "硅烷偶联剂季度出货量(当前Q1 13469吨，验证高增可持续性)", "SOD一期40吨/年建设进度(2027Q1试生产是否如期)"]
  }
}
